MANIFEST.in
README.rst
config-template.yaml
setup.py
metzoo/__init__.py
metzoo/plugins/__init__.py
metzoo/plugins/txt_estacion_puan.py
metzoo_python_parser_txt_estacion_puan_plugin.egg-info/PKG-INFO
metzoo_python_parser_txt_estacion_puan_plugin.egg-info/SOURCES.txt
metzoo_python_parser_txt_estacion_puan_plugin.egg-info/dependency_links.txt
metzoo_python_parser_txt_estacion_puan_plugin.egg-info/not-zip-safe
metzoo_python_parser_txt_estacion_puan_plugin.egg-info/top_level.txt