Metadata-Version: 1.1
Name: metzoo-python-parser-txt-estacion-puan-plugin
Version: 0.0.3
Summary: Puan meteorology station TXT parser Pluigin for Metzoo
Home-page: https://bitbucket.org/edrans/metzoo-python-parser-txt-estacion-puan-plugin
Author: Edrans
Author-email: info@edrans.com
License: MIT
Keywords: metzoo monitoring metric parser
Platform: UNKNOWN
Classifier: Development Status :: 4 - Beta
Classifier: License :: OSI Approved :: MIT License
Classifier: Programming Language :: Python :: 2.7
